transix/__init__.py
transix/transforms/__init__.py
transix/transforms/fortescue.py
transix-0.0.1.dist-info/licenses/LICENSE
transix-0.0.1.dist-info/WHEEL
transix-0.0.1.dist-info/METADATA
transix-0.0.1.dist-info/RECORD
