Metadata-Version: 2.4
Name: transix
Version: 0.0.1
Summary: A lightweight toolkit for numerical transformations
Keywords: numerical,transformations,math,engineering,scientific,transforms
Author: Gowtham Mahendran
Author-email: Gowtham Mahendran <gowtham.mahendran@outlook.com>
License-Expression: MIT
License-File: LICENSE
Classifier: Development Status :: 3 - Alpha
Classifier: Intended Audience :: Science/Research
Classifier: Intended Audience :: Developers
Classifier: Topic :: Scientific/Engineering
Classifier: License :: OSI Approved :: MIT License
Classifier: Operating System :: OS Independent
Classifier: Programming Language :: Python :: 3
Classifier: Programming Language :: Python :: 3 :: Only
Classifier: Programming Language :: Python :: 3.12
Classifier: Programming Language :: Python :: 3.13
Classifier: Programming Language :: Python :: 3.14
Requires-Dist: numpy>=2.0
Requires-Dist: pytest>=9.0 ; extra == 'dev'
Requires-Dist: ruff>=0.14 ; extra == 'dev'
Requires-Python: >=3.12
Project-URL: Homepage, https://github.com/Gowtham-Mahendran/transix
Project-URL: Repository, https://github.com/Gowtham-Mahendran/transix
Project-URL: Issues, https://github.com/Gowtham-Mahendran/transix/issues
Provides-Extra: dev
